tarifafedextest/apiservice.py
tarifafedextest/cotizatarifa.py
tarifafedextest/main.py
tarifafedextest/settings.py
tarifafedextest-0.5.dist-info/METADATA
tarifafedextest-0.5.dist-info/WHEEL
tarifafedextest-0.5.dist-info/top_level.txt
tarifafedextest-0.5.dist-info/RECORD
