Metadata-Version: 2.1
Name: tarifafedextest
Version: 0.5
Summary: Test de tarifa fedex. Prueba para Manuable
Home-page: https://github.com/jasso208/tarifafedextest.git
Author: Javier Jasso
Author-email: jasso.gallegos@gmail.com
License: MIT
